[{"text": "Java", "link": "http://www.lagou.com/zhaopin/Java?labelWords=label"},
{"text": "C++", "link": "http://www.lagou.com/zhaopin/C%2B%2B?labelWords=label"},
{"text": "PHP", "link": "http://www.lagou.com/zhaopin/PHP?labelWords=label"},
{"text": "\u6570\u636e\u6316\u6398", "link": "http://www.lagou.com/zhaopin/shujuwajue?labelWords=label"},
{"text": "\u81ea\u7136\u8bed\u8a00\u5904\u7406", "link": "http://www.lagou.com/zhaopin/ziranyuyanchuli?labelWords=label"},
{"text": "\u641c\u7d22\u7b97\u6cd5", "link": "http://www.lagou.com/zhaopin/sousuosuanfa?labelWords=label"},
{"text": "\u7cbe\u51c6\u63a8\u8350", "link": "http://www.lagou.com/zhaopin/jingzhuntuijian?labelWords=label"},
{"text": "C", "link": "http://www.lagou.com/zhaopin/C?labelWords=label"},
{"text": "C#", "link": "http://www.lagou.com/zhaopin/C%23?labelWords=label"},
{"text": "\u5168\u6808\u5de5\u7a0b\u5e08", "link": "http://www.lagou.com/zhaopin/quanzhangongchengshi?labelWords=label"},
{"text": ".NET", "link": "http://www.lagou.com/zhaopin/.NET?labelWords=label"},
{"text": "Hadoop", "link": "http://www.lagou.com/zhaopin/Hadoop?labelWords=label"},
{"text": "Python", "link": "http://www.lagou.com/zhaopin/Python?labelWords=label"},
{"text": "Delphi", "link": "http://www.lagou.com/zhaopin/Delphi?labelWords=label"},
{"text": "VB", "link": "http://www.lagou.com/zhaopin/VB?labelWords=label"},
{"text": "Perl", "link": "http://www.lagou.com/zhaopin/Perl?labelWords=label"},
{"text": "Ruby", "link": "http://www.lagou.com/zhaopin/Ruby?labelWords=label"},
{"text": "Node.js", "link": "http://www.lagou.com/zhaopin/Node.js?labelWords=label"},
{"text": "Go", "link": "http://www.lagou.com/zhaopin/go?labelWords=label"},
{"text": "ASP", "link": "http://www.lagou.com/zhaopin/asp?labelWords=label"},
{"text": "Shell", "link": "http://www.lagou.com/zhaopin/shell?labelWords=label"},
{"text": "\u540e\u7aef\u5f00\u53d1\u5176\u5b83", "link": "http://www.lagou.com/zhaopin/houduankaifaqita?labelWords=label"},
{"text": "HTML5", "link": "http://www.lagou.com/zhaopin/HTML5?labelWords=label"},
{"text": "Android", "link": "http://www.lagou.com/zhaopin/Android?labelWords=label"},
{"text": "iOS", "link": "http://www.lagou.com/zhaopin/iOS?labelWords=label"},
{"text": "WP", "link": "http://www.lagou.com/zhaopin/WP?labelWords=label"},
{"text": "\u79fb\u52a8\u5f00\u53d1\u5176\u5b83", "link": "http://www.lagou.com/zhaopin/yidongkaifaqita?labelWords=label"},
{"text": "web\u524d\u7aef", "link": "http://www.lagou.com/zhaopin/webqianduan?labelWords=label"},
{"text": "Flash", "link": "http://www.lagou.com/zhaopin/Flash?labelWords=label"},
{"text": "html5", "link": "http://www.lagou.com/zhaopin/html51?labelWords=label"},
{"text": "JavaScript", "link": "http://www.lagou.com/zhaopin/JavaScript?labelWords=label"},
{"text": "U3D", "link": "http://www.lagou.com/zhaopin/U3D?labelWords=label"},
{"text": "COCOS2D-X", "link": "http://www.lagou.com/zhaopin/COCOS2D-X?labelWords=label"},
{"text": "\u524d\u7aef\u5f00\u53d1\u5176\u5b83", "link": "http://www.lagou.com/zhaopin/qianduankaifaqita?labelWords=label"},
{"text": "\u786c\u4ef6", "link": "http://www.lagou.com/zhaopin/yingjian?labelWords=label"},
{"text": "\u5d4c\u5165\u5f0f", "link": "http://www.lagou.com/zhaopin/qianrushi?labelWords=label"},
{"text": "\u81ea\u52a8\u5316", "link": "http://www.lagou.com/zhaopin/zidonghua?labelWords=label"},
{"text": "\u5355\u7247\u673a", "link": "http://www.lagou.com/zhaopin/danpianji?labelWords=label"},
{"text": "\u7535\u8def\u8bbe\u8ba1", "link": "http://www.lagou.com/zhaopin/dianlusheji?labelWords=label"},
{"text": "\u9a71\u52a8\u5f00\u53d1", "link": "http://www.lagou.com/zhaopin/qudongkaifa?labelWords=label"},
{"text": "\u7cfb\u7edf\u96c6\u6210", "link": "http://www.lagou.com/zhaopin/xitongjicheng?labelWords=label"},
{"text": "FPGA\u5f00\u53d1", "link": "http://www.lagou.com/zhaopin/fpgakaifa?labelWords=label"},
{"text": "DSP\u5f00\u53d1", "link": "http://www.lagou.com/zhaopin/dspkaifa?labelWords=label"},
{"text": "ARM\u5f00\u53d1", "link": "http://www.lagou.com/zhaopin/armkaifa?labelWords=label"},
{"text": "PCB\u5de5\u827a", "link": "http://www.lagou.com/zhaopin/pcbgongyi?labelWords=label"},
{"text": "\u6a21\u5177\u8bbe\u8ba1", "link": "http://www.lagou.com/zhaopin/mujusheji?labelWords=label"},
{"text": "\u70ed\u4f20\u5bfc", "link": "http://www.lagou.com/zhaopin/rechuandao?labelWords=label"},
{"text": "\u6750\u6599\u5de5\u7a0b\u5e08", "link": "http://www.lagou.com/zhaopin/cailiaogongchengshi?labelWords=label"},
{"text": "\u7cbe\u76ca\u5de5\u7a0b\u5e08", "link": "http://www.lagou.com/zhaopin/jingyigongchengshi?labelWords=label"},
{"text": "\u5c04\u9891\u5de5\u7a0b\u5e08", "link": "http://www.lagou.com/zhaopin/shepingongchengshi?labelWords=label"},
{"text": "\u786c\u4ef6\u5f00\u53d1\u5176\u5b83", "link": "http://www.lagou.com/zhaopin/yingjiankaifaqita?labelWords=label"},
{"text": "\u6d4b\u8bd5\u5de5\u7a0b\u5e08", "link": "http://www.lagou.com/zhaopin/ceshigongchengshi?labelWords=label"},
{"text": "\u81ea\u52a8\u5316\u6d4b\u8bd5", "link": "http://www.lagou.com/zhaopin/zidonghuaceshi?labelWords=label"},
{"text": "\u529f\u80fd\u6d4b\u8bd5", "link": "http://www.lagou.com/zhaopin/gongnengceshi?labelWords=label"},
{"text": "\u6027\u80fd\u6d4b\u8bd5", "link": "http://www.lagou.com/zhaopin/xingnengceshi?labelWords=label"},
{"text": "\u6d4b\u8bd5\u5f00\u53d1", "link": "http://www.lagou.com/zhaopin/ceshikaifa?labelWords=label"},
{"text": "\u6e38\u620f\u6d4b\u8bd5", "link": "http://www.lagou.com/zhaopin/youxiceshi?labelWords=label"},
{"text": "\u767d\u76d2\u6d4b\u8bd5", "link": "http://www.lagou.com/zhaopin/baiheceshi?labelWords=label"},
{"text": "\u7070\u76d2\u6d4b\u8bd5", "link": "http://www.lagou.com/zhaopin/huiheceshi?labelWords=label"},
{"text": "\u9ed1\u76d2\u6d4b\u8bd5", "link": "http://www.lagou.com/zhaopin/heiheceshi?labelWords=label"},
{"text": "\u624b\u673a\u6d4b\u8bd5", "link": "http://www.lagou.com/zhaopin/shoujiceshi?labelWords=label"},
{"text": "\u786c\u4ef6\u6d4b\u8bd5", "link": "http://www.lagou.com/zhaopin/yingjianceshi?labelWords=label"},
{"text": "\u6d4b\u8bd5\u7ecf\u7406", "link": "http://www.lagou.com/zhaopin/ceshijingli2?labelWords=label"},
{"text": "\u6d4b\u8bd5\u5176\u5b83", "link": "http://www.lagou.com/zhaopin/ceshiqita?labelWords=label"},
{"text": "\u8fd0\u7ef4\u5de5\u7a0b\u5e08", "link": "http://www.lagou.com/zhaopin/yunweigongchengshi?labelWords=label"},
{"text": "\u8fd0\u7ef4\u5f00\u53d1\u5de5\u7a0b\u5e08", "link": "http://www.lagou.com/zhaopin/yunweikaifagongchengshi?labelWords=label"},
{"text": "\u7f51\u7edc\u5de5\u7a0b\u5e08", "link": "http://www.lagou.com/zhaopin/wangluogongchengshi?labelWords=label"},
{"text": "\u7cfb\u7edf\u5de5\u7a0b\u5e08", "link": "http://www.lagou.com/zhaopin/xitonggongchengshi?labelWords=label"},
{"text": "IT\u652f\u6301", "link": "http://www.lagou.com/zhaopin/ITzhichi?labelWords=label"},
{"text": "IDC", "link": "http://www.lagou.com/zhaopin/idc?labelWords=label"},
{"text": "CDN", "link": "http://www.lagou.com/zhaopin/cdn?labelWords=label"},
{"text": "F5", "link": "http://www.lagou.com/zhaopin/f5?labelWords=label"},
{"text": "\u7cfb\u7edf\u7ba1\u7406\u5458", "link": "http://www.lagou.com/zhaopin/xitongguanliyuan?labelWords=label"},
{"text": "\u75c5\u6bd2\u5206\u6790", "link": "http://www.lagou.com/zhaopin/bingdufenxi?labelWords=label"},
{"text": "WEB\u5b89\u5168", "link": "http://www.lagou.com/zhaopin/webanquan?labelWords=label"},
{"text": "\u7f51\u7edc\u5b89\u5168", "link": "http://www.lagou.com/zhaopin/wangluoanquan?labelWords=label"},
{"text": "\u7cfb\u7edf\u5b89\u5168", "link": "http://www.lagou.com/zhaopin/xitonganquan?labelWords=label"},
{"text": "\u8fd0\u7ef4\u7ecf\u7406", "link": "http://www.lagou.com/zhaopin/yunweijingli?labelWords=label"},
{"text": "\u8fd0\u7ef4\u5176\u5b83", "link": "http://www.lagou.com/zhaopin/yunweiqita?labelWords=label"},
{"text": "MySQL", "link": "http://www.lagou.com/zhaopin/MySQL?labelWords=label"},
{"text": "SQLServer", "link": "http://www.lagou.com/zhaopin/SQLServer?labelWords=label"},
{"text": "Oracle", "link": "http://www.lagou.com/zhaopin/Oracle?labelWords=label"},
{"text": "DB2", "link": "http://www.lagou.com/zhaopin/DB2?labelWords=label"},
{"text": "MongoDB", "link": "http://www.lagou.com/zhaopin/MongoDB?labelWords=label"},
{"text": "ETL", "link": "http://www.lagou.com/zhaopin/etl?labelWords=label"},
{"text": "Hive", "link": "http://www.lagou.com/zhaopin/hive?labelWords=label"},
{"text": "\u6570\u636e\u4ed3\u5e93", "link": "http://www.lagou.com/zhaopin/shujucangku?labelWords=label"},
{"text": "DBA\u5176\u5b83", "link": "http://www.lagou.com/zhaopin/dbaqita?labelWords=label"},
{"text": "\u9879\u76ee\u7ecf\u7406", "link": "http://www.lagou.com/zhaopin/xiangmujingli?labelWords=label"},
{"text": "\u9879\u76ee\u52a9\u7406", "link": "http://www.lagou.com/zhaopin/xiangmuzhuli?labelWords=label"},
{"text": "\u5b9e\u65bd\u5de5\u7a0b\u5e08", "link": "http://www.lagou.com/zhaopin/shishigongchengshi?labelWords=label"},
{"text": "\u552e\u524d\u5de5\u7a0b\u5e08", "link": "http://www.lagou.com/zhaopin/shouqiangongchengshi?labelWords=label"},
{"text": "\u552e\u540e\u5de5\u7a0b\u5e08", "link": "http://www.lagou.com/zhaopin/shouhougongchengshi?labelWords=label"},
{"text": "BI\u5de5\u7a0b\u5e08", "link": "http://www.lagou.com/zhaopin/bigongchengshi?labelWords=label"},
{"text": "\u4f01\u4e1a\u8f6f\u4ef6\u5176\u5b83", "link": "http://www.lagou.com/zhaopin/qiyeruanjianqita?labelWords=label"},
{"text": "\u6280\u672f\u7ecf\u7406", "link": "http://www.lagou.com/zhaopin/jishujingli?labelWords=label"},
{"text": "\u6280\u672f\u603b\u76d1", "link": "http://www.lagou.com/zhaopin/jishuzongjian?labelWords=label"},
{"text": "\u67b6\u6784\u5e08", "link": "http://www.lagou.com/zhaopin/jiagoushi?labelWords=label"},
{"text": "CTO", "link": "http://www.lagou.com/zhaopin/CTO?labelWords=label"},
{"text": "\u8fd0\u7ef4\u603b\u76d1", "link": "http://www.lagou.com/zhaopin/yunweizongjian?labelWords=label"},
{"text": "\u6280\u672f\u5408\u4f19\u4eba", "link": "http://www.lagou.com/zhaopin/jishuhehuoren?labelWords=label"},
{"text": "\u9879\u76ee\u603b\u76d1", "link": "http://www.lagou.com/zhaopin/xiangmuzongjian?labelWords=label"},
{"text": "\u6d4b\u8bd5\u603b\u76d1", "link": "http://www.lagou.com/zhaopin/ceshizongjian?labelWords=label"},
{"text": "\u5b89\u5168\u4e13\u5bb6", "link": "http://www.lagou.com/zhaopin/anquanzhuanjia?labelWords=label"},
{"text": "\u9ad8\u7aef\u6280\u672f\u804c\u4f4d\u5176\u5b83", "link": "http://www.lagou.com/zhaopin/gaoduanjishuzhiweiqita?labelWords=label"},
{"text": "\u4ea7\u54c1\u7ecf\u7406", "link": "http://www.lagou.com/zhaopin/chanpinjingli1?labelWords=label"},
{"text": "\u7f51\u9875\u4ea7\u54c1\u7ecf\u7406", "link": "http://www.lagou.com/zhaopin/wangyechanpinjingli?labelWords=label"},
{"text": "\u79fb\u52a8\u4ea7\u54c1\u7ecf\u7406", "link": "http://www.lagou.com/zhaopin/yidongchanpinjingli?labelWords=label"},
{"text": "\u4ea7\u54c1\u52a9\u7406", "link": "http://www.lagou.com/zhaopin/chanpinzhuli?labelWords=label"},
{"text": "\u6570\u636e\u4ea7\u54c1\u7ecf\u7406", "link": "http://www.lagou.com/zhaopin/shujuchanpinjingli?labelWords=label"},
{"text": "\u7535\u5546\u4ea7\u54c1\u7ecf\u7406", "link": "http://www.lagou.com/zhaopin/dianshangchanpinjingli?labelWords=label"},
{"text": "\u6e38\u620f\u7b56\u5212", "link": "http://www.lagou.com/zhaopin/youxicehua?labelWords=label"},
{"text": "\u4ea7\u54c1\u5b9e\u4e60\u751f", "link": "http://www.lagou.com/zhaopin/chanpinshixisheng?labelWords=label"},
{"text": "\u7f51\u9875\u4ea7\u54c1\u8bbe\u8ba1\u5e08", "link": "http://www.lagou.com/zhaopin/wangyechanpinshejishi?labelWords=label"},
{"text": "\u65e0\u7ebf\u4ea7\u54c1\u8bbe\u8ba1\u5e08", "link": "http://www.lagou.com/zhaopin/wuxianchanpinshejishi?labelWords=label"},
{"text": "\u4ea7\u54c1\u90e8\u7ecf\u7406", "link": "http://www.lagou.com/zhaopin/chanpinbujingli?labelWords=label"},
{"text": "\u4ea7\u54c1\u603b\u76d1", "link": "http://www.lagou.com/zhaopin/chanpinzongjian?labelWords=label"},
{"text": "\u6e38\u620f\u5236\u4f5c\u4eba", "link": "http://www.lagou.com/zhaopin/youxizhizuoren?labelWords=label"},
{"text": "\u89c6\u89c9\u8bbe\u8ba1\u5e08", "link": "http://www.lagou.com/zhaopin/shijueshejishi?labelWords=label"},
{"text": "\u7f51\u9875\u8bbe\u8ba1\u5e08", "link": "http://www.lagou.com/zhaopin/wangyeshejishi?labelWords=label"},
{"text": "Flash\u8bbe\u8ba1\u5e08", "link": "http://www.lagou.com/zhaopin/Flashshejishi?labelWords=label"},
{"text": "APP\u8bbe\u8ba1\u5e08", "link": "http://www.lagou.com/zhaopin/APPshejishi?labelWords=label"},
{"text": "UI\u8bbe\u8ba1\u5e08", "link": "http://www.lagou.com/zhaopin/UIshejishi?labelWords=label"},
{"text": "\u5e73\u9762\u8bbe\u8ba1\u5e08", "link": "http://www.lagou.com/zhaopin/pingmianshejishi?labelWords=label"},
{"text": "\u7f8e\u672f\u8bbe\u8ba1\u5e08\uff082D/3D\uff09", "link": "http://www.lagou.com/zhaopin/meishushejishi%EF%BC%882D3D%EF%BC%89?labelWords=label"},
{"text": "\u5e7f\u544a\u8bbe\u8ba1\u5e08", "link": "http://www.lagou.com/zhaopin/guanggaoshejishi?labelWords=label"},
{"text": "\u591a\u5a92\u4f53\u8bbe\u8ba1\u5e08", "link": "http://www.lagou.com/zhaopin/duomeitishejishi?labelWords=label"},
{"text": "\u539f\u753b\u5e08", "link": "http://www.lagou.com/zhaopin/yuanhuashi?labelWords=label"},
{"text": "\u6e38\u620f\u7279\u6548", "link": "http://www.lagou.com/zhaopin/youxitexiao?labelWords=label"},
{"text": "\u6e38\u620f\u754c\u9762\u8bbe\u8ba1\u5e08", "link": "http://www.lagou.com/zhaopin/youxijiemianshejishi?labelWords=label"},
{"text": "\u6e38\u620f\u573a\u666f", "link": "http://www.lagou.com/zhaopin/youxichangjing?labelWords=label"},
{"text": "\u6e38\u620f\u89d2\u8272", "link": "http://www.lagou.com/zhaopin/youxijiaose?labelWords=label"},
{"text": "\u6e38\u620f\u52a8\u4f5c", "link": "http://www.lagou.com/zhaopin/youxidongzuo?labelWords=label"},
{"text": "\u4ea4\u4e92\u8bbe\u8ba1\u5e08", "link": "http://www.lagou.com/zhaopin/jiaohushejishi1?labelWords=label"},
{"text": "\u65e0\u7ebf\u4ea4\u4e92\u8bbe\u8ba1\u5e08", "link": "http://www.lagou.com/zhaopin/wuxianjiaohushejishi?labelWords=label"},
{"text": "\u7f51\u9875\u4ea4\u4e92\u8bbe\u8ba1\u5e08", "link": "http://www.lagou.com/zhaopin/wangyejiaohushejishi?labelWords=label"},
{"text": "\u786c\u4ef6\u4ea4\u4e92\u8bbe\u8ba1\u5e08", "link": "http://www.lagou.com/zhaopin/yingjianjiaohushejishi?labelWords=label"},
{"text": "\u6570\u636e\u5206\u6790\u5e08", "link": "http://www.lagou.com/zhaopin/shujufenxishi?labelWords=label"},
{"text": "\u7528\u6237\u7814\u7a76\u5458", "link": "http://www.lagou.com/zhaopin/yonghuyanjiuyuan?labelWords=label"},
{"text": "\u6e38\u620f\u6570\u503c\u7b56\u5212", "link": "http://www.lagou.com/zhaopin/youxishuzhicehua?labelWords=label"},
{"text": "\u8bbe\u8ba1\u7ecf\u7406/\u4e3b\u7ba1", "link": "http://www.lagou.com/zhaopin/shejijinglizhuguan?labelWords=label"},
{"text": "\u8bbe\u8ba1\u603b\u76d1", "link": "http://www.lagou.com/zhaopin/shejizongjian?labelWords=label"},
{"text": "\u89c6\u89c9\u8bbe\u8ba1\u7ecf\u7406/\u4e3b\u7ba1", "link": "http://www.lagou.com/zhaopin/shijueshejijinglizhuguan?labelWords=label"},
{"text": "\u89c6\u89c9\u8bbe\u8ba1\u603b\u76d1", "link": "http://www.lagou.com/zhaopin/shijueshejizongjian?labelWords=label"},
{"text": "\u4ea4\u4e92\u8bbe\u8ba1\u7ecf\u7406/\u4e3b\u7ba1", "link": "http://www.lagou.com/zhaopin/jiaohushejijinglizhuguan?labelWords=label"},
{"text": "\u4ea4\u4e92\u8bbe\u8ba1\u603b\u76d1", "link": "http://www.lagou.com/zhaopin/jiaohushejizongjian?labelWords=label"},
{"text": "\u7528\u6237\u7814\u7a76\u7ecf\u7406/\u4e3b\u7ba1", "link": "http://www.lagou.com/zhaopin/yonghuyanjiujinglizhuguan?labelWords=label"},
{"text": "\u7528\u6237\u7814\u7a76\u603b\u76d1", "link": "http://www.lagou.com/zhaopin/yonghuyanjiuzongjian?labelWords=label"},
{"text": "\u7528\u6237\u8fd0\u8425", "link": "http://www.lagou.com/zhaopin/yonghuyunying?labelWords=label"},
{"text": "\u4ea7\u54c1\u8fd0\u8425", "link": "http://www.lagou.com/zhaopin/chanpinyunying?labelWords=label"},
{"text": "\u6570\u636e\u8fd0\u8425", "link": "http://www.lagou.com/zhaopin/shujuyunying?labelWords=label"},
{"text": "\u5185\u5bb9\u8fd0\u8425", "link": "http://www.lagou.com/zhaopin/neirongyunying?labelWords=label"},
{"text": "\u6d3b\u52a8\u8fd0\u8425", "link": "http://www.lagou.com/zhaopin/huodongyunying?labelWords=label"},
{"text": "\u5546\u5bb6\u8fd0\u8425", "link": "http://www.lagou.com/zhaopin/shangjiayunying?labelWords=label"},
{"text": "\u54c1\u7c7b\u8fd0\u8425", "link": "http://www.lagou.com/zhaopin/pinleiyunying?labelWords=label"},
{"text": "\u6e38\u620f\u8fd0\u8425", "link": "http://www.lagou.com/zhaopin/youxiyunying?labelWords=label"},
{"text": "\u7f51\u7edc\u63a8\u5e7f", "link": "http://www.lagou.com/zhaopin/wangluotuiguang?labelWords=label"},
{"text": "\u8fd0\u8425\u4e13\u5458", "link": "http://www.lagou.com/zhaopin/yunyingzhuanyuan?labelWords=label"},
{"text": "\u7f51\u5e97\u8fd0\u8425", "link": "http://www.lagou.com/zhaopin/wangdianyunying?labelWords=label"},
{"text": "\u65b0\u5a92\u4f53\u8fd0\u8425", "link": "http://www.lagou.com/zhaopin/xinmeitiyunying?labelWords=label"},
{"text": "\u6d77\u5916\u8fd0\u8425", "link": "http://www.lagou.com/zhaopin/haiwaiyunying?labelWords=label"},
{"text": "\u8fd0\u8425\u7ecf\u7406", "link": "http://www.lagou.com/zhaopin/yunyingjingli?labelWords=label"},
{"text": "\u526f\u4e3b\u7f16", "link": "http://www.lagou.com/zhaopin/fuzhubian?labelWords=label"},
{"text": "\u5185\u5bb9\u7f16\u8f91", "link": "http://www.lagou.com/zhaopin/neirongbianji?labelWords=label"},
{"text": "\u6587\u6848\u7b56\u5212", "link": "http://www.lagou.com/zhaopin/wenancehua?labelWords=label"},
{"text": "\u8bb0\u8005", "link": "http://www.lagou.com/zhaopin/jizhe?labelWords=label"},
{"text": "\u552e\u524d\u54a8\u8be2", "link": "http://www.lagou.com/zhaopin/shouqianzixun?labelWords=label"},
{"text": "\u552e\u540e\u5ba2\u670d", "link": "http://www.lagou.com/zhaopin/shouhoukefu?labelWords=label"},
{"text": "\u6dd8\u5b9d\u5ba2\u670d", "link": "http://www.lagou.com/zhaopin/taobaokefu?labelWords=label"},
{"text": "\u5ba2\u670d\u7ecf\u7406", "link": "http://www.lagou.com/zhaopin/kefujingli?labelWords=label"},
{"text": "\u4e3b\u7f16", "link": "http://www.lagou.com/zhaopin/zhubian?labelWords=label"},
{"text": "\u8fd0\u8425\u603b\u76d1", "link": "http://www.lagou.com/zhaopin/yunyingzongjian?labelWords=label"},
{"text": "COO", "link": "http://www.lagou.com/zhaopin/COO?labelWords=label"},
{"text": "\u5ba2\u670d\u603b\u76d1", "link": "http://www.lagou.com/zhaopin/kefuzongjian?labelWords=label"},
{"text": "\u5e02\u573a\u8425\u9500", "link": "http://www.lagou.com/zhaopin/shichangyingxiao1?labelWords=label"},
{"text": "\u5e02\u573a\u7b56\u5212", "link": "http://www.lagou.com/zhaopin/shichangcehua?labelWords=label"},
{"text": "\u5e02\u573a\u987e\u95ee", "link": "http://www.lagou.com/zhaopin/shichangguwen?labelWords=label"},
{"text": "\u5e02\u573a\u63a8\u5e7f", "link": "http://www.lagou.com/zhaopin/shichangtuiguang?labelWords=label"},
{"text": "SEO", "link": "http://www.lagou.com/zhaopin/SEO?labelWords=label"},
{"text": "SEM", "link": "http://www.lagou.com/zhaopin/SEM?labelWords=label"},
{"text": "\u5546\u52a1\u6e20\u9053", "link": "http://www.lagou.com/zhaopin/shangwuqudao?labelWords=label"},
{"text": "\u5546\u4e1a\u6570\u636e\u5206\u6790", "link": "http://www.lagou.com/zhaopin/shangyeshujufenxi?labelWords=label"},
{"text": "\u6d3b\u52a8\u7b56\u5212", "link": "http://www.lagou.com/zhaopin/huodongcehua?labelWords=label"},
{"text": "\u7f51\u7edc\u8425\u9500", "link": "http://www.lagou.com/zhaopin/wangluoyingxiao?labelWords=label"},
{"text": "\u6d77\u5916\u5e02\u573a", "link": "http://www.lagou.com/zhaopin/haiwaishichang?labelWords=label"},
{"text": "\u653f\u5e9c\u5173\u7cfb", "link": "http://www.lagou.com/zhaopin/zhengfuguanxi?labelWords=label"},
{"text": "\u5a92\u4ecb\u7ecf\u7406", "link": "http://www.lagou.com/zhaopin/meijiejingli?labelWords=label"},
{"text": "\u5e7f\u544a\u534f\u8c03", "link": "http://www.lagou.com/zhaopin/guanggaoxiediao?labelWords=label"},
{"text": "\u54c1\u724c\u516c\u5173", "link": "http://www.lagou.com/zhaopin/pinpaigongguan?labelWords=label"},
{"text": "\u9500\u552e\u4e13\u5458", "link": "http://www.lagou.com/zhaopin/xiaoshouzhuanyuan?labelWords=label"},
{"text": "\u9500\u552e\u7ecf\u7406", "link": "http://www.lagou.com/zhaopin/xiaoshoujingli?labelWords=label"},
{"text": "\u5ba2\u6237\u4ee3\u8868", "link": "http://www.lagou.com/zhaopin/kehudaibiao?labelWords=label"},
{"text": "\u5927\u5ba2\u6237\u4ee3\u8868", "link": "http://www.lagou.com/zhaopin/dakehudaibiao?labelWords=label"},
{"text": "BD\u7ecf\u7406", "link": "http://www.lagou.com/zhaopin/BDjingli?labelWords=label"},
{"text": "\u5546\u52a1\u6e20\u9053", "link": "http://www.lagou.com/zhaopin/shangwuqudao1?labelWords=label"},
{"text": "\u6e20\u9053\u9500\u552e", "link": "http://www.lagou.com/zhaopin/qudaoxiaoshou?labelWords=label"},
{"text": "\u4ee3\u7406\u5546\u9500\u552e", "link": "http://www.lagou.com/zhaopin/dailishangxiaoshou?labelWords=label"},
{"text": "\u9500\u552e\u52a9\u7406", "link": "http://www.lagou.com/zhaopin/xiaoshouzhuli?labelWords=label"},
{"text": "\u7535\u8bdd\u9500\u552e", "link": "http://www.lagou.com/zhaopin/dianhuaxiaoshou?labelWords=label"},
{"text": "\u9500\u552e\u987e\u95ee", "link": "http://www.lagou.com/zhaopin/xiaoshouguwen?labelWords=label"},
{"text": "\u5546\u54c1\u7ecf\u7406", "link": "http://www.lagou.com/zhaopin/shangpinzhuli?labelWords=label"},
{"text": "\u7269\u6d41", "link": "http://www.lagou.com/zhaopin/wuliu?labelWords=label"},
{"text": "\u4ed3\u50a8", "link": "http://www.lagou.com/zhaopin/cangchu?labelWords=label"},
{"text": "\u91c7\u8d2d\u4e13\u5458", "link": "http://www.lagou.com/zhaopin/caigouzhuanyuan?labelWords=label"},
{"text": "\u91c7\u8d2d\u7ecf\u7406", "link": "http://www.lagou.com/zhaopin/caigoujingli?labelWords=label"},
{"text": "\u5546\u54c1\u7ecf\u7406", "link": "http://www.lagou.com/zhaopin/shangpinjingli?labelWords=label"},
{"text": "\u5206\u6790\u5e08", "link": "http://www.lagou.com/zhaopin/fenxishi?labelWords=label"},
{"text": "\u6295\u8d44\u987e\u95ee", "link": "http://www.lagou.com/zhaopin/touziguwen?labelWords=label"},
{"text": "\u6295\u8d44\u7ecf\u7406", "link": "http://www.lagou.com/zhaopin/touzijingli?labelWords=label"},
{"text": "\u5e02\u573a\u603b\u76d1", "link": "http://www.lagou.com/zhaopin/shichangzongjian?labelWords=label"},
{"text": "\u9500\u552e\u603b\u76d1", "link": "http://www.lagou.com/zhaopin/xiaoshouzongjian?labelWords=label"},
{"text": "\u5546\u52a1\u603b\u76d1", "link": "http://www.lagou.com/zhaopin/shangwuzongjian?labelWords=label"},
{"text": "CMO", "link": "http://www.lagou.com/zhaopin/CMO?labelWords=label"},
{"text": "\u516c\u5173\u603b\u76d1", "link": "http://www.lagou.com/zhaopin/gongguanzongjian?labelWords=label"},
{"text": "\u91c7\u8d2d\u603b\u76d1", "link": "http://www.lagou.com/zhaopin/caigouzongjian?labelWords=label"},
{"text": "\u6295\u8d44\u603b\u76d1", "link": "http://www.lagou.com/zhaopin/touzizongjian?labelWords=label"},
{"text": "\u4eba\u529b\u8d44\u6e90", "link": "http://www.lagou.com/zhaopin/renliziyuan1?labelWords=label"},
{"text": "\u62db\u8058", "link": "http://www.lagou.com/zhaopin/zhaopin?labelWords=label"},
{"text": "HRBP", "link": "http://www.lagou.com/zhaopin/HRBP?labelWords=label"},
{"text": "\u4eba\u4e8b/HR", "link": "http://www.lagou.com/zhaopin/renshiHR?labelWords=label"},
{"text": "\u57f9\u8bad\u7ecf\u7406", "link": "http://www.lagou.com/zhaopin/peixunjingli?labelWords=label"},
{"text": "\u85aa\u8d44\u798f\u5229\u7ecf\u7406", "link": "http://www.lagou.com/zhaopin/xinzifulijingli?labelWords=label"},
{"text": "\u7ee9\u6548\u8003\u6838\u7ecf\u7406", "link": "http://www.lagou.com/zhaopin/jixiaokaohejingli?labelWords=label"},
{"text": "\u5458\u5de5\u5173\u7cfb", "link": "http://www.lagou.com/zhaopin/yuangongguanxi?labelWords=label"},
{"text": "\u52a9\u7406", "link": "http://www.lagou.com/zhaopin/zhuli?labelWords=label"},
{"text": "\u524d\u53f0", "link": "http://www.lagou.com/zhaopin/qiantai?labelWords=label"},
{"text": "\u884c\u653f", "link": "http://www.lagou.com/zhaopin/xingzheng1?labelWords=label"},
{"text": "\u603b\u52a9", "link": "http://www.lagou.com/zhaopin/zongzhu?labelWords=label"},
{"text": "\u6587\u79d8", "link": "http://www.lagou.com/zhaopin/wenmi?labelWords=label"},
{"text": "\u4f1a\u8ba1", "link": "http://www.lagou.com/zhaopin/kuaiji?labelWords=label"},
{"text": "\u51fa\u7eb3", "link": "http://www.lagou.com/zhaopin/chuna?labelWords=label"},
{"text": "\u8d22\u52a1", "link": "http://www.lagou.com/zhaopin/caiwu1?labelWords=label"},
{"text": "\u7ed3\u7b97", "link": "http://www.lagou.com/zhaopin/jiesuan?labelWords=label"},
{"text": "\u7a0e\u52a1", "link": "http://www.lagou.com/zhaopin/shuiwu?labelWords=label"},
{"text": "\u5ba1\u8ba1", "link": "http://www.lagou.com/zhaopin/shenji?labelWords=label"},
{"text": "\u98ce\u63a7", "link": "http://www.lagou.com/zhaopin/fengkong?labelWords=label"},
{"text": "\u6cd5\u52a1", "link": "http://www.lagou.com/zhaopin/fawu2?labelWords=label"},
{"text": "\u5f8b\u5e08", "link": "http://www.lagou.com/zhaopin/lvshi?labelWords=label"},
{"text": "\u4e13\u5229", "link": "http://www.lagou.com/zhaopin/zhuanli?labelWords=label"},
{"text": "\u884c\u653f\u603b\u76d1/\u7ecf\u7406", "link": "http://www.lagou.com/zhaopin/xingzhengzongjianjingli?labelWords=label"},
{"text": "\u8d22\u52a1\u603b\u76d1/\u7ecf\u7406", "link": "http://www.lagou.com/zhaopin/caiwuzongjianjingli?labelWords=label"},
{"text": "HRD/HRM", "link": "http://www.lagou.com/zhaopin/HRDHRM?labelWords=label"},
{"text": "CFO", "link": "http://www.lagou.com/zhaopin/CFO?labelWords=label"},
{"text": "CEO", "link": "http://www.lagou.com/zhaopin/ceo?labelWords=label"}]